shimsim/__init__.py
shimsim-0.1.0.dist-info/WHEEL
shimsim-0.1.0.dist-info/entry_points.txt
shimsim-0.1.0.dist-info/METADATA
shimsim-0.1.0.dist-info/RECORD
